{
	"info": {
		"_postman_id": "5f5ffa7c-1318-48d7-9340-92949b33aad5",
		"name": "ChartOfAccounts",
		"schema": "https://schema.getpostman.com/json/collection/v2.1.0/collection.json",
		"_exporter_id": "8217839"
	},
	"item": [
		{
			"name": "GET ChartOfAccounts",
			"request": {
				"method": "GET",
				"header": [],
				"url": {
					"raw": "http://localhost:17728/api/chartofaccounts",
					"protocol": "http",
					"host": [
						"localhost"
					],
					"port": "17728",
					"path": [
						"api",
						"chartofaccounts"
					]
				}
			},
			"response": []
		},
		{
			"name": "GET ChartOfAccount",
			"request": {
				"method": "GET",
				"header": [],
				"url": {
					"raw": "http://localhost:17728/api/chartofaccounts",
					"protocol": "http",
					"host": [
						"localhost"
					],
					"port": "17728",
					"path": [
						"api",
						"chartofaccounts"
					]
				}
			},
			"response": []
		},
		{
			"name": "GET ChartGroups",
			"request": {
				"method": "GET",
				"header": [],
				"url": {
					"raw": "http://localhost:17728/api/chartofaccounts",
					"protocol": "http",
					"host": [
						"localhost"
					],
					"port": "17728",
					"path": [
						"api",
						"chartofaccounts"
					]
				}
			},
			"response": []
		},
		{
			"name": "GET ChartGroup",
			"request": {
				"method": "GET",
				"header": [],
				"url": {
					"raw": "http://localhost:17728/api/chartofaccounts",
					"protocol": "http",
					"host": [
						"localhost"
					],
					"port": "17728",
					"path": [
						"api",
						"chartofaccounts"
					]
				}
			},
			"response": []
		},
		{
			"name": "POST ChartGroup",
			"request": {
				"method": "POST",
				"header": [],
				"body": {
					"mode": "raw",
					"raw": "{\r\n    \"description\": \"Retained Earnings\"\r\n}",
					"options": {
						"raw": {
							"language": "json"
						}
					}
				},
				"url": {
					"raw": "http://localhost:17728/api/chartofaccounts/2/chartgroup",
					"protocol": "http",
					"host": [
						"localhost"
					],
					"port": "17728",
					"path": [
						"api",
						"chartofaccounts",
						"2",
						"chartgroup"
					]
				}
			},
			"response": []
		},
		{
			"name": "PUT ChartGroup",
			"request": {
				"method": "PUT",
				"header": [],
				"body": {
					"mode": "raw",
					"raw": "{\r\n    \"description\": \"Retained Earnings\"\r\n}",
					"options": {
						"raw": {
							"language": "json"
						}
					}
				},
				"url": {
					"raw": "http://localhost:17728/api/chartofaccounts/2/chartgroup",
					"protocol": "http",
					"host": [
						"localhost"
					],
					"port": "17728",
					"path": [
						"api",
						"chartofaccounts",
						"2",
						"chartgroup"
					]
				}
			},
			"response": []
		},
		{
			"name": "PATCH ChartGroup",
			"request": {
				"method": "PATCH",
				"header": [],
				"body": {
					"mode": "raw",
					"raw": "[\r\n    {\r\n      \"op\": \"replace\",\r\n      \"path\": \"/description\",\r\n      \"value\": \"Account Payable Subsidiary\"\r\n    }\r\n]",
					"options": {
						"raw": {
							"language": "json"
						}
					}
				},
				"url": {
					"raw": "http://localhost:17728/api/chartofaccounts/2/chartgroup/4",
					"protocol": "http",
					"host": [
						"localhost"
					],
					"port": "17728",
					"path": [
						"api",
						"chartofaccounts",
						"2",
						"chartgroup",
						"4"
					]
				}
			},
			"response": []
		},
		{
			"name": "DELETE ChartGroup",
			"request": {
				"method": "DELETE",
				"header": [],
				"body": {
					"mode": "raw",
					"raw": "[\r\n    {\r\n      \"op\": \"replace\",\r\n      \"path\": \"/description\",\r\n      \"value\": \"Account Payable Subsidiary\"\r\n    }\r\n]",
					"options": {
						"raw": {
							"language": "json"
						}
					}
				},
				"url": {
					"raw": "http://localhost:17728/api/chartofaccounts/2/chartgroup/4",
					"protocol": "http",
					"host": [
						"localhost"
					],
					"port": "17728",
					"path": [
						"api",
						"chartofaccounts",
						"2",
						"chartgroup",
						"4"
					]
				}
			},
			"response": []
		}
	]
}